yunuscaly/__init__.py
yunuscaly-0.0.1.dist-info/LICENSE
yunuscaly-0.0.1.dist-info/METADATA
yunuscaly-0.0.1.dist-info/WHEEL
yunuscaly-0.0.1.dist-info/top_level.txt
yunuscaly-0.0.1.dist-info/RECORD
