Metadata-Version: 2.1
Name: yunuscaly
Version: 0.0.1
Summary: This package will help you to do  calculations quickly.
Home-page: https://github.com/Md9291/yunuscaly
Author: MOHAMMAD YUNUS
Author-email: md.yunus.9291@gmail.com
License: UNKNOWN
Project-URL: Bug Tracker, https://github.com/Md9291/yunuscaly/issues
Platform: UNKNOWN
Classifier: Programming Language :: Python :: 3
Classifier: License :: OSI Approved :: MIT License
Classifier: Operating System :: OS Independent
Requires-Python: >=3.10
License-File: LICENSE
